MANIFEST.in
README.rst
setup.py
analytics/__init__.py
analytics/templatetags/__init__.py
analytics/templatetags/analytics_tags.py
django_google_analytics_id.egg-info/PKG-INFO
django_google_analytics_id.egg-info/SOURCES.txt
django_google_analytics_id.egg-info/dependency_links.txt
django_google_analytics_id.egg-info/top_level.txt
tests/__init__.py
tests/models.py
tests/test_settings.py
tests/tests.py